{
  "dataSource" : {
    "pagesize" : "25",
    "SQL" : "SELECT ENTRYID ,COM0DEST ,ENTRYDATE,SEQNO,COMMSG1 ,PRINTIND  FROM PMSLCLCMT1",
    "filename" : "PMSLCLCMT1",
    "type" : "SQL"
  },
  "gridMetaData" : {
    "operation" : {
      "options" : " ,Change,Delete,Display,Reprint,Suppress Print",
      "jsfunction" : "doClaimActivity(this.value, this.parentNode.parentNode)"
    },
    "element" : [ {
      "field" : "ENTRYID ",
      "visible" : "true",
      "width" : "10%",
      "align" : "center",
      "displayName" : "Requester"
    }, {
      "field" : "COM0DEST ",
      "visible" : "true",
      "width" : "10%",
      "align" : "center",
      "displayName" : "Destination"
    }, {
      "field" : "ENTRYDATE",
      "visible" : "true",
      "width" : "10%",
      "align" : "center",
      "displayName" : "Date"
    }, {
      "field" : "SEQNO",
      "visible" : "true",
      "width" : "10%",
      "align" : "center",
      "displayName" : "Sequence"
    }, {
      "field" : "COMMSG1 ",
      "visible" : "true",
      "width" : "10%",
      "align" : "left",
      "displayName" : "Message"
    }, {
      "field" : "PRINTIND ",
      "visible" : "true",
      "width" : "10%",
      "align" : "center",
      "displayName" : "Printed"
    } ],
    "title" : "Claim Comments"
  }
}