{
    "metadata":  {
                     "groupid":  "BASE",
                     "formid":  "EzcFrame",
                     "defaultsubmitresetbuttons":  "No",
                     "title":  "EZDataCapture Utility - Data Capture Details ",
                     "section":  [
                                     {
                                         "sectionsize":  "12",
                                         "subsection":  [
                                                            {
                                                                "subsectiontitle":  "",
                                                                "element":  [
                                                                                {
                                                                                    "name":  "WS_EZT_LOC",
                                                                                    "type":  "select",
                                                                                    "order":  "7",
                                                                                    "placeholder":  "",
                                                                                    "maxlength":  "2",
                                                                                    "minlength":  "0",
                                                                                    "fieldspan":  6,
                                                                                    "size":  10,
                                                                                    "autoformat":  "true",
                                                                                    "parentField":  "Field",
                                                                                    "help":  "none",
                                                                                    "disabled":  "true",
                                                                                    "properties":  [

                                                                                                   ],
                                                                                    "options":  [
                                                                                                    {
                                                                                                        "description":  "Default LOC(99)",
                                                                                                        "value":  "99"
                                                                                                    }
                                                                                                ],
                                                                                    "support":  "true",
                                                                                    "label":  "LOC",
                                                                                    "reference":  "",
                                                                                    "page":  "EzcKeyHeader2",
                                                                                    "defaultValue":  ""
                                                                                },
                                                                                {
                                                                                    "name":  "WS_EZT_LOB",
                                                                                    "type":  "select",
                                                                                    "order":  "7",
                                                                                    "placeholder":  "",
                                                                                    "maxlength":  "2",
                                                                                    "minlength":  "0",
                                                                                    "fieldspan":  6,
                                                                                    "size":  10,
                                                                                    "autoformat":  "true",
                                                                                    "parentField":  "Field",
                                                                                    "help":  "none",
                                                                                    "properties":  [

                                                                                                   ],
                                                                                    "disabled":  "true",
                                                                                    "options":  [
                                                                                                    {
                                                                                                        "description":  "",
                                                                                                        "value":  ""
                                                                                                    }
                                                                                                ],
                                                                                    "support":  "true",
                                                                                    "label":  "Line of Business",
                                                                                    "reference":  "",
                                                                                    "page":  "EzcKeyHeader2",
                                                                                    "defaultValue":  ""
                                                                                },
                                                                                {
                                                                                    "name":  "WS_EZT_MCO",
                                                                                    "type":  "select",
                                                                                    "order":  "7",
                                                                                    "placeholder":  "",
                                                                                    "maxlength":  "2",
                                                                                    "minlength":  "0",
                                                                                    "fieldspan":  6,
                                                                                    "support":  "true",
                                                                                    "size":  10,
                                                                                    "autoformat":  "true",
                                                                                    "parentField":  "Field",
                                                                                    "help":  "none",
                                                                                    "properties":  [

                                                                                                   ],
                                                                                    "disabled":  "true",
                                                                                    "options":  [
                                                                                                    {
                                                                                                        "description":  "",
                                                                                                        "value":  ""
                                                                                                    }
                                                                                                ],
                                                                                    "label":  "MCO",
                                                                                    "reference":  "",
                                                                                    "page":  "EzcKeyHeader2",
                                                                                    "defaultValue":  ""
                                                                                },
                                                                                {
                                                                                    "name":  "WS_EZT_STATE",
                                                                                    "type":  "select",
                                                                                    "order":  "10",
                                                                                    "placeholder":  "",
                                                                                    "maxlength":  "2",
                                                                                    "minlength":  "0",
                                                                                    "fieldspan":  6,
                                                                                    "size":  10,
                                                                                    "autoformat":  "true",
                                                                                    "parentField":  "Field",
                                                                                    "help":  "none",
                                                                                    "properties":  [

                                                                                                   ],
                                                                                    "disabled":  "true",
                                                                                    "options":  [
                                                                                                    {
                                                                                                        "description":  "",
                                                                                                        "value":  ""
                                                                                                    }
                                                                                                ],
                                                                                    "support":  "true",
                                                                                    "label":  "State",
                                                                                    "reference":  "",
                                                                                    "page":  "EzcKeyHeader2",
                                                                                    "defaultValue":  ""
                                                                                },
                                                                                {
                                                                                    "name":  "WS_EZT_PCO",
                                                                                    "type":  "select",
                                                                                    "order":  "7",
                                                                                    "placeholder":  "",
                                                                                    "support":  "true",
                                                                                    "maxlength":  "2",
                                                                                    "minlength":  "0",
                                                                                    "fieldspan":  12,
                                                                                    "size":  5,
                                                                                    "autoformat":  "true",
                                                                                    "parentField":  "Field",
                                                                                    "help":  "none",
                                                                                    "properties":  [
                                                                                                       {
                                                                                                           "name":  "indicator",
                                                                                                           "value":  "update"
                                                                                                       }
                                                                                                   ],
                                                                                    "disabled":  "true",
                                                                                    "options":  [
                                                                                                    {
                                                                                                        "description":  "",
                                                                                                        "value":  ""
                                                                                                    }
                                                                                                ],
                                                                                    "label":  "PCO",
                                                                                    "selectedoption":  {
                                                                                                           "description":  "",
                                                                                                           "value":  ""
                                                                                                       },
                                                                                    "reference":  "",
                                                                                    "page":  "EzcKeyHeader2",
                                                                                    "defaultValue":  ""
                                                                                },
                                                                                {
                                                                                    "name":  "WS_EZT_SCRN_TYP",
                                                                                    "type":  "select",
                                                                                    "label":  "Capture Type",
                                                                                    "order":  "10",
                                                                                    "disabled":  "true",
                                                                                    "placeholder":  "",
                                                                                    "options":  [
                                                                                                    {
                                                                                                        "value":  "FORM",
                                                                                                        "description":  "FORM"
                                                                                                    },
                                                                                                    {
                                                                                                        "value":  "DATA",
                                                                                                        "description":  "DATA"
                                                                                                    }
                                                                                                ],
                                                                                    "fieldspan":  2,
                                                                                    "size":  11,
                                                                                    "required":  "required",
                                                                                    "parentField":  "Field",
                                                                                    "help":  "none",
                                                                                    "properties":  [
                                                                                                       {
                                                                                                           "name":  "indicator",
                                                                                                           "value":  "update"
                                                                                                       }
                                                                                                   ],
                                                                                    "selectedoption":  {
                                                                                                           "value":  "FORM",
                                                                                                           "description":  "FORM"
                                                                                                       },
                                                                                    "reference":  "",
                                                                                    "page":  "EzcKeyHeader2",
                                                                                    "defaultValue":  ""
                                                                                },
                                                                                {
                                                                                    "name":  "WS_EZT_FORMID",
                                                                                    "type":  "text",
                                                                                    "disabled":  "true",
                                                                                    "label":  "Capture ID",
                                                                                    "order":  "31",
                                                                                    "placeholder":  "",
                                                                                    "fieldspan":  2,
                                                                                    "size":  12,
                                                                                    "parentField":  "Field",
                                                                                    "help":  "none",
                                                                                    "properties":  [
                                                                                                       {
                                                                                                           "name":  "indicator",
                                                                                                           "value":  "update"
                                                                                                       }
                                                                                                   ],
                                                                                    "reference":  "",
                                                                                    "page":  "EzcKeyHeader2",
                                                                                    "defaultValue":  ""
                                                                                },
                                                                                {
                                                                                    "name":  "WS_EZT_VERSION",
                                                                                    "type":  "text",
                                                                                    "label":  "Ver",
                                                                                    "order":  "31",
                                                                                    "placeholder":  "",
                                                                                    "disabled":  "true",
                                                                                    "fieldspan":  1,
                                                                                    "size":  12,
                                                                                    "parentField":  "Field",
                                                                                    "help":  "none",
                                                                                    "properties":  [
                                                                                                       {
                                                                                                           "name":  "indicator",
                                                                                                           "value":  "update"
                                                                                                       }
                                                                                                   ],
                                                                                    "reference":  "",
                                                                                    "page":  "EzcKeyHeader2",
                                                                                    "defaultValue":  ""
                                                                                },
                                                                                {
                                                                                    "name":  "WS_EZT_EDITION",
                                                                                    "type":  "text",
                                                                                    "label":  "Edition Date",
                                                                                    "disabled":  "true",
                                                                                    "order":  "31",
                                                                                    "placeholder":  "",
                                                                                    "fieldspan":  2,
                                                                                    "size":  12,
                                                                                    "parentField":  "Field",
                                                                                    "help":  "none",
                                                                                    "properties":  [
                                                                                                       {
                                                                                                           "name":  "indicator",
                                                                                                           "value":  "update"
                                                                                                       }
                                                                                                   ],
                                                                                    "reference":  "",
                                                                                    "page":  "EzcKeyHeader2",
                                                                                    "defaultValue":  ""
                                                                                },
                                                                                {
                                                                                    "name":  "WS_EZT_EFFDTE",
                                                                                    "type":  "date",
                                                                                    "label":  "Effective Date",
                                                                                    "disabled":  "true",
                                                                                    "order":  "31",
                                                                                    "placeholder":  "",
                                                                                    "fieldspan":  3,
                                                                                    "size":  12,
                                                                                    "parentField":  "Field",
                                                                                    "help":  "none",
                                                                                    "properties":  [
                                                                                                       {
                                                                                                           "name":  "indicator",
                                                                                                           "value":  "update"
                                                                                                       }
                                                                                                   ],
                                                                                    "reference":  "",
                                                                                    "page":  "EzcKeyHeader2",
                                                                                    "defaultValue":  ""
                                                                                },
                                                                                {
                                                                                    "name":  "WS_EZT_EXPDTE",
                                                                                    "type":  "date",
                                                                                    "label":  "Expiration Date",
                                                                                    "order":  "31",
                                                                                    "placeholder":  "",
                                                                                    "disabled":  "true",
                                                                                    "fieldspan":  3,
                                                                                    "size":  12,
                                                                                    "parentField":  "Field",
                                                                                    "help":  "none",
                                                                                    "properties":  [
                                                                                                       {
                                                                                                           "name":  "indicator",
                                                                                                           "value":  "update"
                                                                                                       }
                                                                                                   ],
                                                                                    "reference":  "",
                                                                                    "page":  "EzcKeyHeader2",
                                                                                    "defaultValue":  ""
                                                                                },
                                                                                {
                                                                                    "name":  "GroupEzFrameButtons",
                                                                                    "type":  "grouptext",
                                                                                    "fieldspan":  "11",
                                                                                    "controlgroup":  [
                                                                                                         {
                                                                                                             "name":  "ID_EzckeyHeader2_NewElement_Button",
                                                                                                             "label":  "New Element",
                                                                                                             "type":  "button",
                                                                                                             "size":  "3",
                                                                                                             "reference":  "",
                                                                                                             "page":  "EzcKeyHeader2",
                                                                                                             "defaultValue":  ""
                                                                                                         },
                                                                                                         {
                                                                                                             "name":  "ID_EzckeyHeader2_Test_Button",
                                                                                                             "label":  "Test",
                                                                                                             "type":  "button",
                                                                                                             "size":  "3",
                                                                                                             "reference":  "",
                                                                                                             "page":  "EzcKeyHeader2",
                                                                                                             "defaultValue":  ""
                                                                                                         },
                                                                                                         {
                                                                                                             "name":  "ID_EzckeyHeader2_Back_Button",
                                                                                                             "label":  "Back",
                                                                                                             "type":  "button",
                                                                                                             "size":  "3",
                                                                                                             "reference":  "",
                                                                                                             "page":  "EzcKeyHeader2",
                                                                                                             "defaultValue":  ""
                                                                                                         }
                                                                                                     ]
                                                                                },
                                                                                {
                                                                                    "name":  "EzcDetailGrid",
                                                                                    "type":  "grid",
                                                                                    "label":  "EzcFrame Search",
                                                                                    "fieldspan":  "12",
                                                                                    "gridId":  "EzcDetailGrid",
                                                                                    "parentField":  "Field",
                                                                                    "help":  "none",
                                                                                    "properties":  [
                                                                                                       {
                                                                                                           "name":  "indicator",
                                                                                                           "value":  "update"
                                                                                                       }
                                                                                                   ],
                                                                                    "reference":  "",
                                                                                    "page":  "EzcKeyHeader2",
                                                                                    "defaultValue":  ""
                                                                                }
                                                                            ]
                                                            },
                                                            {
                                                                "title":  "NewElementClick",
                                                                "element":  [
                                                                                {
                                                                                    "label":  "Seq. Number",
                                                                                    "name":  "WS_EZT_ELEMENT_NO",
                                                                                    "fieldspan":  2,
                                                                                    "type":  "text",
                                                                                    "size":  12,
                                                                                    "required":  "required",
                                                                                    "parentField":  "Field",
                                                                                    "help":  "none",
                                                                                    "properties":  [
                                                                                                       {
                                                                                                           "name":  "indicator",
                                                                                                           "value":  "update"
                                                                                                       }
                                                                                                   ],
                                                                                    "reference":  "",
                                                                                    "page":  "EzcKeyHeader2",
                                                                                    "defaultValue":  ""
                                                                                },
                                                                                {
                                                                                    "name":  "WS_EZT_EL_NAME",
                                                                                    "label":  "Name",
                                                                                    "labelspan":  "8",
                                                                                    "fieldspan":  "6",
                                                                                    "type":  "text",
                                                                                    "size":  7,
                                                                                    "parentField":  "Field",
                                                                                    "help":  "none",
                                                                                    "properties":  [
                                                                                                       {
                                                                                                           "name":  "indicator",
                                                                                                           "value":  "update"
                                                                                                       }
                                                                                                   ],
                                                                                    "reference":  "",
                                                                                    "page":  "EzcKeyHeader2",
                                                                                    "defaultValue":  ""
                                                                                },
                                                                                {
                                                                                    "label":  "Label",
                                                                                    "name":  "WS_EZT_LABEL",
                                                                                    "labelspan":  "8",
                                                                                    "fieldspan":  "6",
                                                                                    "type":  "text",
                                                                                    "properties":  [
                                                                                                       {
                                                                                                           "name":  "indicator",
                                                                                                           "value":  "add"
                                                                                                       },
                                                                                                       {
                                                                                                           "name":  "SC_CODE",
                                                                                                           "value":  " "
                                                                                                       },
                                                                                                       {
                                                                                                           "name":  "USRENTRYFIELD",
                                                                                                           "value":  ""
                                                                                                       },
                                                                                                       {
                                                                                                           "name":  "PRINTIND",
                                                                                                           "value":  " "
                                                                                                       },
                                                                                                       {
                                                                                                           "name":  "REQUIRED_PT",
                                                                                                           "value":  " "
                                                                                                       },
                                                                                                       {
                                                                                                           "name":  "INDD",
                                                                                                           "value":  ""
                                                                                                       },
                                                                                                       {
                                                                                                           "name":  "ERRORCD",
                                                                                                           "value":  ""
                                                                                                       }
                                                                                                   ],
                                                                                    "parentField":  "Field",
                                                                                    "help":  "none",
                                                                                    "reference":  "",
                                                                                    "page":  "EzcKeyHeader2",
                                                                                    "defaultValue":  ""
                                                                                },
                                                                                {
                                                                                    "name":  "WS_EZT_LABEL",
                                                                                    "label":  "",
                                                                                    "type":  "textarea",
                                                                                    "parentField":  "Field",
                                                                                    "help":  "none",
                                                                                    "properties":  [
                                                                                                       {
                                                                                                           "name":  "indicator",
                                                                                                           "value":  "update"
                                                                                                       }
                                                                                                   ],
                                                                                    "reference":  "",
                                                                                    "page":  "EzcKeyHeader2",
                                                                                    "defaultValue":  ""
                                                                                },
                                                                                {
                                                                                    "name":  "WS_EZT_EL_TYPE",
                                                                                    "label":  "Data Type",
                                                                                    "labelspan":  "8",
                                                                                    "fieldspan":  3,
                                                                                    "type":  "select",
                                                                                    "options":  [
                                                                                                    {
                                                                                                        "value":  "text",
                                                                                                        "description":  "Text"
                                                                                                    },
                                                                                                    {
                                                                                                        "value":  "date",
                                                                                                        "description":  "Date"
                                                                                                    },
                                                                                                    {
                                                                                                        "value":  "money",
                                                                                                        "description":  "Money"
                                                                                                    },
                                                                                                    {
                                                                                                        "value":  "number",
                                                                                                        "description":  "Number"
                                                                                                    },
                                                                                                    {
                                                                                                        "value":  "checkbox",
                                                                                                        "description":  "Checkbox"
                                                                                                    },
                                                                                                    {
                                                                                                        "value":  "pdf",
                                                                                                        "description":  "PDF"
                                                                                                    },
                                                                                                    {
                                                                                                        "value":  "textarea",
                                                                                                        "description":  "Textarea"
                                                                                                    },
                                                                                                    {
                                                                                                        "value":  "button",
                                                                                                        "description":  "Button"
                                                                                                    },
                                                                                                    {
                                                                                                        "value":  "piName",
                                                                                                        "description":  "Policy Interest Name"
                                                                                                    },
                                                                                                    {
                                                                                                        "value":  "piAdd1",
                                                                                                        "description":  "Policy Interest Add 1"
                                                                                                    },
                                                                                                    {
                                                                                                        "value":  "piAdd2",
                                                                                                        "description":  "Policy Interest Add 2"
                                                                                                    },
                                                                                                    {
                                                                                                        "value":  "piCitySt",
                                                                                                        "description":  "Policy Interest Cty/St"
                                                                                                    },
                                                                                                    {
                                                                                                        "value":  "piZip",
                                                                                                        "description":  "Policy Interest Zip"
                                                                                                    },
                                                                                                    {
                                                                                                        "value":  "piType",
                                                                                                        "description":  "Policy Interest Type"
                                                                                                    },
                                                                                                    {
                                                                                                        "value":  "piLoc",
                                                                                                        "description":  "Policy Interest Loc"
                                                                                                    },
                                                                                                    {
                                                                                                        "value":  "piSubLoc",
                                                                                                        "description":  "Policy Interest SubLoc"
                                                                                                    },
                                                                                                    {
                                                                                                        "value":  "smModType",
                                                                                                        "description":  "State Mod Type"
                                                                                                    },
                                                                                                    {
                                                                                                        "value":  "ccClassCd",
                                                                                                        "description":  "Emp Class Code"
                                                                                                    },
                                                                                                    {
                                                                                                        "value":  "ccClassSeq",
                                                                                                        "description":  "Emp Class Code Seq"
                                                                                                    }
                                                                                                ],
                                                                                    "parentField":  "Field",
                                                                                    "help":  "none",
                                                                                    "properties":  [
                                                                                                       {
                                                                                                           "name":  "indicator",
                                                                                                           "value":  "update"
                                                                                                       }
                                                                                                   ],
                                                                                    "selectedoption":  {
                                                                                                           "value":  "text",
                                                                                                           "description":  "Text"
                                                                                                       },
                                                                                    "size":  11,
                                                                                    "reference":  "",
                                                                                    "page":  "EzcKeyHeader2",
                                                                                    "defaultValue":  ""
                                                                                },
                                                                                {
                                                                                    "label":  "Search",
                                                                                    "name":  "btnPi",
                                                                                    "labelspan":  "8",
                                                                                    "fieldspan":  8,
                                                                                    "type":  "button",
                                                                                    "parentField":  "Field",
                                                                                    "help":  "none",
                                                                                    "size":  3,
                                                                                    "properties":  [
                                                                                                       {
                                                                                                           "name":  "indicator",
                                                                                                           "value":  "update"
                                                                                                       }
                                                                                                   ],
                                                                                    "reference":  "",
                                                                                    "page":  "EzcKeyHeader2",
                                                                                    "defaultValue":  ""
                                                                                },
                                                                                {
                                                                                    "name":  "WS_EZT_MAX_LGTH",
                                                                                    "label":  "Max Length",
                                                                                    "labelspan":  "8",
                                                                                    "fieldspan":  4,
                                                                                    "type":  "text",
                                                                                    "help":  "none",
                                                                                    "parentField":  "Field",
                                                                                    "properties":  [
                                                                                                       {
                                                                                                           "name":  "indicator",
                                                                                                           "value":  "update"
                                                                                                       }
                                                                                                   ],
                                                                                    "size":  8,
                                                                                    "reference":  "",
                                                                                    "page":  "EzcKeyHeader2",
                                                                                    "defaultValue":  ""
                                                                                },
                                                                                {
                                                                                    "label":  "Mask",
                                                                                    "name":  "WS_EZT_EL_MASK",
                                                                                    "labelspan":  "8",
                                                                                    "fieldspan":  8,
                                                                                    "type":  "select",
                                                                                    "options":  [
                                                                                                    {
                                                                                                        "value":  "mm/dd/yyyy",
                                                                                                        "description":  "mm/dd/yyyy"
                                                                                                    },
                                                                                                    {
                                                                                                        "value":  "999-999-9999",
                                                                                                        "description":  "999-999-9999"
                                                                                                    }
                                                                                                ],
                                                                                    "parentField":  "Field",
                                                                                    "help":  "none",
                                                                                    "properties":  [
                                                                                                       {
                                                                                                           "name":  "indicator",
                                                                                                           "value":  "update"
                                                                                                       }
                                                                                                   ],
                                                                                    "selectedoption":  {
                                                                                                           "value":  "mm/dd/yyyy",
                                                                                                           "description":  "mm/dd/yyyy"
                                                                                                       },
                                                                                    "size":  3,
                                                                                    "reference":  "",
                                                                                    "page":  "EzcKeyHeader2",
                                                                                    "defaultValue":  ""
                                                                                },
                                                                                {
                                                                                    "label":  "Decimal Places",
                                                                                    "name":  "WS_EZT_DECIMALS",
                                                                                    "labelspan":  "8",
                                                                                    "fieldspan":  3,
                                                                                    "type":  "select",
                                                                                    "options":  [
                                                                                                    {
                                                                                                        "value":  "0",
                                                                                                        "description":  "0"
                                                                                                    },
                                                                                                    {
                                                                                                        "value":  "2",
                                                                                                        "description":  "2"
                                                                                                    },
                                                                                                    {
                                                                                                        "value":  "5",
                                                                                                        "description":  "5"
                                                                                                    }
                                                                                                ],
                                                                                    "parentField":  "Field",
                                                                                    "help":  "none",
                                                                                    "properties":  [
                                                                                                       {
                                                                                                           "name":  "indicator",
                                                                                                           "value":  "update"
                                                                                                       }
                                                                                                   ],
                                                                                    "selectedoption":  {
                                                                                                           "value":  "0",
                                                                                                           "description":  "0"
                                                                                                       },
                                                                                    "size":  11,
                                                                                    "reference":  "",
                                                                                    "page":  "EzcKeyHeader2",
                                                                                    "defaultValue":  ""
                                                                                },
                                                                                {
                                                                                    "label":  "Currency Symbol",
                                                                                    "labelspan":  "8",
                                                                                    "fieldspan":  3,
                                                                                    "type":  "select",
                                                                                    "name":  "WS_EZT_CURENCY",
                                                                                    "options":  [
                                                                                                    {
                                                                                                        "value":  "Y",
                                                                                                        "description":  "Yes"
                                                                                                    },
                                                                                                    {
                                                                                                        "value":  "N",
                                                                                                        "description":  "No"
                                                                                                    }
                                                                                                ],
                                                                                    "required":  "false",
                                                                                    "parentField":  "Field",
                                                                                    "help":  "none",
                                                                                    "properties":  [
                                                                                                       {
                                                                                                           "name":  "indicator",
                                                                                                           "value":  "update"
                                                                                                       }
                                                                                                   ],
                                                                                    "selectedoption":  {
                                                                                                           "value":  "Y",
                                                                                                           "description":  "Yes"
                                                                                                       },
                                                                                    "size":  9,
                                                                                    "reference":  "",
                                                                                    "page":  "EzcKeyHeader2",
                                                                                    "defaultValue":  ""
                                                                                },
                                                                                {
                                                                                    "label":  "Required",
                                                                                    "name":  "WS_EZT_REQUIRD",
                                                                                    "labelspan":  "8",
                                                                                    "fieldspan":  3,
                                                                                    "type":  "select",
                                                                                    "options":  [
                                                                                                    {
                                                                                                        "value":  "Y",
                                                                                                        "description":  "Yes"
                                                                                                    },
                                                                                                    {
                                                                                                        "value":  "N",
                                                                                                        "description":  "No"
                                                                                                    }
                                                                                                ],
                                                                                    "parentField":  "Field",
                                                                                    "help":  "none",
                                                                                    "reference":  "",
                                                                                    "page":  "EzcKeyHeader2",
                                                                                    "defaultValue":  ""
                                                                                },
                                                                                {
                                                                                    "label":  "Initial Value",
                                                                                    "name":  "WS_EZT_INIT_VAL",
                                                                                    "labelspan":  "8",
                                                                                    "fieldspan":  12,
                                                                                    "type":  "text",
                                                                                    "parentField":  "Field",
                                                                                    "help":  "none",
                                                                                    "size":  6,
                                                                                    "reference":  "",
                                                                                    "page":  "EzcKeyHeader2",
                                                                                    "defaultValue":  ""
                                                                                },
                                                                                {
                                                                                    "label":  "Help Text or Sel PI Types",
                                                                                    "labelspan":  "8",
                                                                                    "name":  "WS_EZT_HELP",
                                                                                    "fieldspan":  6,
                                                                                    "type":  "text",
                                                                                    "parentField":  "Field",
                                                                                    "help":  "none",
                                                                                    "properties":  [
                                                                                                       {
                                                                                                           "name":  "indicator",
                                                                                                           "value":  "update"
                                                                                                       }
                                                                                                   ],
                                                                                    "size":  12,
                                                                                    "reference":  "",
                                                                                    "page":  "EzcKeyHeader2",
                                                                                    "defaultValue":  ""
                                                                                },
                                                                                {
                                                                                    "name":  "EzcKeyHeader2buttons",
                                                                                    "type":  "grouptext",
                                                                                    "fieldspan":  "11",
                                                                                    "controlgroup":  [
                                                                                                         {
                                                                                                             "name":  "ID_EzcKeyHeader2_Save_Button",
                                                                                                             "label":  "Submit",
                                                                                                             "type":  "submit",
                                                                                                             "size":  "2",
                                                                                                             "reference":  "",
                                                                                                             "page":  "EzcKeyHeader2",
                                                                                                             "defaultValue":  ""
                                                                                                         },
                                                                                                         {
                                                                                                             "name":  "ID_EzcKeyHeader2_Cancel_Button",
                                                                                                             "label":  "Cancel",
                                                                                                             "type":  "button",
                                                                                                             "size":  "3",
                                                                                                             "reference":  "",
                                                                                                             "page":  "EzcKeyHeader2",
                                                                                                             "defaultValue":  ""
                                                                                                         },
                                                                                                         {
                                                                                                             "name":  "ID_EzcKeyHeader2_Reset_Button",
                                                                                                             "label":  "Reset",
                                                                                                             "type":  "button",
                                                                                                             "size":  "3",
                                                                                                             "reference":  "",
                                                                                                             "page":  "EzcKeyHeader2",
                                                                                                             "defaultValue":  ""
                                                                                                         }
                                                                                                     ]
                                                                                }
                                                                            ]
                                                            }
                                                        ]
                                     },
                                     {
                                         "sectionsize":  "12",
                                         "subsection":  [

                                                        ]
                                     }
                                 ]
                 }
}
